safe_redirect_url/__init__.py
safe_redirect_url-0.1.1.dist-info/METADATA
safe_redirect_url-0.1.1.dist-info/WHEEL
safe_redirect_url-0.1.1.dist-info/licenses/LICENSE
safe_redirect_url-0.1.1.dist-info/RECORD
