Metadata-Version: 2.1
Name: safe-redirect-url
Version: 0.1.1
Summary: Check the safety of a redirect URL. Extracted from Django's `url_has_allowed_host_and_scheme`.
Project-URL: Documentation, https://frankie567.github.io/safe-redirect-url/
Project-URL: Source, https://github.com/frankie567/safe-redirect-url
Author-email: safe-redirect-url <fvoron@gmail.com>
License-File: LICENSE
Classifier: Programming Language :: Python :: 3 :: Only
Requires-Python: >=3.11
